setup.py
krux_redis/__init__.py
krux_redis.egg-info/PKG-INFO
krux_redis.egg-info/SOURCES.txt
krux_redis.egg-info/dependency_links.txt
krux_redis.egg-info/requires.txt
krux_redis.egg-info/top_level.txt