Metadata-Version: 1.1
Name: krux-redis
Version: 0.0.3
Summary: Library to wrap redsi.py for writers & multiple readers
Home-page: https://github.com/krux/python-krux-redis
Author: Jos Boumans
Author-email: jos@krux.com
License: All Rights Reserved.
Download-URL: https://github.com/krux/python-krux-redis/tarball/release/0.0.3
Platform: UNKNOWN
